termpass/arguments.py
termpass/color.py
termpass/conf.py
termpass/crypt.py
termpass/functions.py
termpass/inputs.py
termpass/interpreter.py
termpass/start.py
termpass-1.2.data/scripts/termpass
termpass-1.2.dist-info/LICENSE
termpass-1.2.dist-info/METADATA
termpass-1.2.dist-info/WHEEL
termpass-1.2.dist-info/top_level.txt
termpass-1.2.dist-info/RECORD
