Metadata-Version: 2.1
Name: termpass
Version: 1.2
Summary: Gnupg based password manager
Author: JeSeLLo
Author-email: cebrailbilgic95@gmail.com
Classifier: License :: OSI Approved :: GNU General Public License v3 (GPLv3)
Classifier: Operating System :: OS Independent
Classifier: Programming Language :: Python
License-File: LICENSE
Requires-Dist: python-gnupg
Requires-Dist: termcolor
